{
  "basics": {
    "name": "Ioan Andrés Muñoz",
    "label": "Desarrollador fullstack con experiencia en brindar soluciones personalizadas",
    "image": "https://avatars.githubusercontent.com/u/141512518?v=4",
    "email": "jaguerx88@gmail.com",
    "phone": "(+57) 317-868-4451",
    "summary": "Desarrollador fullstack certificado con experiencia resolviendo necesidades de clientes específicos como Instituciones Educativas, negocios pequeños y medianos.",
    "location": {
      "city": "Pitalito",
      "countryCode": "CO",
      "region": "Huila"
    },
    "profiles": [
      {
        "network": "GitHub",
        "username": "IAM-DEV88",
        "url": "https://github.com/IAM-DEV88/"
      },
      {
        "network": "LinkedIn",
        "username": "IAM-DEV88",
        "url": "https://www.linkedin.com/in/iam-dev88"
      }
    ]
  },
  "work": [
    {
      "name": "Desarrollo Web",
      "position": "Freelance fullstack developer",
      "startDate": "2023-10-18",
      "endDate": null,
      "highlights": [
        "Desarrollo de páginas y aplicaciones web personalizadas."
      ]
    },{
      "name": "InCall",
      "position": "Especialista de operaciones bilingüe",
      "startDate": "2021-08-17",
      "endDate": "2023-06-26",
      "highlights": [
        "Procesamiento de cotizaciones, despachos y tracking de movimientos de carga en Canadá y Estados Unidos."
      ]
    },
    {
      "name": "TelePerformance",
      "position": "Asesor comercial bilingüe",
      "startDate": "2020-11-05",
      "endDate": "2021-04-14",
      "highlights": [
        "Procesamiento de cotizaciones, despachos y tracking de entregas en Estados Unidos."
      ]
    }
  ],
  "projects": [
    {
      "name": "Administrador de tienda",
      "url": "https://github.com/IAM-DEV88/AdminTiendaWeb",
      "description": "Administrador de tienda en el navegador con control de usuarios, registro contable, de facturación e inventarios",
      "highlights": [
        "CRUD",
        "HTML",
        "CSS",
        "JavaScript"
      ]
    },
    {
      "name": "Agenda Contable",
      "url": "https://github.com/IAM-DEV88/agendareact",
      "description": "Agenda de turnos con registros en libro mayor contable",
      "highlights": [
        "CRUD",
        "Node",
        "React",
        "Axios",
        "Express",
        "MongoDB",
        "G Cloud"
      ]
    },
    {
      "name": "QuickName",
      "url": "https://github.com/IAM-DEV88/QuickName",
      "description": "Addon para comunicacion en World of Warcraft 3.3.5a",
      "highlights": [
        "LUA"
      ]
    }
  ],
  "skills": [
    {
      "name": "Ingles B2+"
    },
    {
      "name": "HTML"
    },
    {
      "name": "CSS"
    },
    {
      "name": "JavaScript"
    },
    {
      "name": "Node"
    },
    {
      "name": "Git"
    },
    {
      "name": "GitHub"
    },
    {
      "name": "React"
    },
    {
      "name": "Astro"
    },
    {
      "name": "Atención al Cliente"
    }
  ]
}
